OCITextSimilarity/OCITextSimilarity.py
OCITextSimilarity/__init__.py
OCITextSimilarity-0.1.0.dist-info/METADATA
OCITextSimilarity-0.1.0.dist-info/WHEEL
OCITextSimilarity-0.1.0.dist-info/top_level.txt
OCITextSimilarity-0.1.0.dist-info/RECORD
